aws_orga_deployer/__init__.py
aws_orga_deployer/cli.py
aws_orga_deployer/config.py
aws_orga_deployer/execution.py
aws_orga_deployer/main.py
aws_orga_deployer/modules.py
aws_orga_deployer/orga.py
aws_orga_deployer/utils.py
aws_orga_deployer/engines/__init__.py
aws_orga_deployer/engines/base.py
aws_orga_deployer/engines/cloudformation.py
aws_orga_deployer/engines/python.py
aws_orga_deployer/engines/terraform.py
aws_orga_deployer/engines/wrappers/__init__.py
aws_orga_deployer/engines/wrappers/base.py
aws_orga_deployer/engines/wrappers/cloudformation.py
aws_orga_deployer/engines/wrappers/python.py
aws_orga_deployer/package/__init__.py
aws_orga_deployer/package/graph.py
aws_orga_deployer/package/schema.py
aws_orga_deployer/package/store.py
aws_orga_deployer-0.1.8.dist-info/licenses/LICENSE.txt
aws_orga_deployer-0.1.8.dist-info/METADATA
aws_orga_deployer-0.1.8.dist-info/WHEEL
aws_orga_deployer-0.1.8.dist-info/entry_points.txt
aws_orga_deployer-0.1.8.dist-info/top_level.txt
aws_orga_deployer-0.1.8.dist-info/RECORD
