Metadata-Version: 2.4
Name: aws-orga-deployer
Version: 0.1.8
Summary: Deploy infrastructure-as-code at the scale of an AWS organization
Home-page: https://github.com/malaval/aws-orga-deployer/
Author: Nicolas Malaval
Author-email: malavaln@gmail.com
Project-URL: Documentation, https://malaval.github.io/aws-orga-deployer/
Classifier: Programming Language :: Python :: 3
Classifier: License :: OSI Approved :: MIT License
Classifier: Operating System :: OS Independent
Requires-Python: >=3.8
License-File: LICENSE.txt
Requires-Dist: boto3
Requires-Dist: pyyaml
Requires-Dist: networkx
Requires-Dist: jsonschema
Provides-Extra: dev
Requires-Dist: coverage; extra == "dev"
Requires-Dist: black==23.*; extra == "dev"
Requires-Dist: isort==5.13.*; extra == "dev"
Requires-Dist: isort[pyproject]; extra == "dev"
Requires-Dist: mypy==1.11.*; extra == "dev"
Requires-Dist: pylint==3.3.*; extra == "dev"
Requires-Dist: pytest; extra == "dev"
Requires-Dist: types-jsonschema; extra == "dev"
Requires-Dist: moto[cloudformation,organizations,s3,server,ssm,sts]==4.*; extra == "dev"
Requires-Dist: build; extra == "dev"
Requires-Dist: twine; extra == "dev"
Dynamic: license-file
